hyly_shims.py
hyly_shim-0.0.15.dist-info/METADATA
hyly_shim-0.0.15.dist-info/WHEEL
hyly_shim-0.0.15.dist-info/top_level.txt
hyly_shim-0.0.15.dist-info/RECORD
