Metadata-Version: 2.1
Name: hyly-shim
Version: 0.0.15
Summary: UNKNOWN
Home-page: https://github.com/munishgandhi/openai_token_usage
Author: Rama Challa
Author-email: rama@hy.ly
License: UNKNOWN
Platform: UNKNOWN
Requires-Dist: langchain
Requires-Dist: mysql-connector-python
Requires-Dist: openai
Requires-Dist: requests
Requires-Dist: tiktoken
